README.md
setup.py
iris_cm_api/__init__.py
iris_cm_api/__main__.py
iris_cm_api/const.py
iris_cm_api/middlewares.py
iris_cm_api/models.py
iris_cm_api/utils.py
iris_cm_api.egg-info/PKG-INFO
iris_cm_api.egg-info/SOURCES.txt
iris_cm_api.egg-info/dependency_links.txt
iris_cm_api.egg-info/requires.txt
iris_cm_api.egg-info/top_level.txt
iris_cm_api/handlers/__init__.py
iris_cm_api/handlers/add_duty.py
iris_cm_api/handlers/add_to_chat.py
iris_cm_api/handlers/connect.py
iris_cm_api/handlers/delete_messages.py
iris_cm_api/handlers/enable.py
iris_cm_api/handlers/info.py
iris_cm_api/handlers/send_signal.py
iris_cm_api/handlers/set_id.py
iris_cm_api/handlers/transcript.py