Metadata-Version: 2.1
Name: iris-cm-api
Version: 0.2.0
Summary: Эмулятор сигналов Iris CM Callback API
Home-page: https://github.com/lordralinc/iris_cm_api_emulator
Author: lordralinc
License: MIT
Platform: UNKNOWN
Classifier: Programming Language :: Python :: 3.7
Classifier: Programming Language :: Python :: 3.8
Classifier: Programming Language :: Python :: 3.9
Classifier: Operating System :: OS Independent
